fileops/__init__.py
fileops/__main__.py
fileops/cli.py
fileops/database/__init__.py
fileops/database/database.py
fileops/database/file.py
fileops/database/filter.py
fileops/database/producer.py
fileops/database/recorder.py
fileops/files/__init__.py
fileops/files/file.py
fileops/files/filter.py
fileops/files/hasher.py
fileops/files/printer.py
fileops/files/producer.py
fileops/pipe/__init__.py
fileops/pipe/operator.py
fileops/pipe/pipe.py
file_ops-1.0.4.dist-info/LICENSE
file_ops-1.0.4.dist-info/METADATA
file_ops-1.0.4.dist-info/WHEEL
file_ops-1.0.4.dist-info/entry_points.txt
file_ops-1.0.4.dist-info/top_level.txt
file_ops-1.0.4.dist-info/RECORD
