Metadata-Version: 2.1
Name: file-ops
Version: 1.0.4
Summary: Filesystem operations to index files and hash their contents
Home-page: https://github.com/Vafilor/file-ops
Author: Andrey Melnikov
Author-email: vafilor@gmail.com
License: UNKNOWN
Platform: UNKNOWN
Classifier: Programming Language :: Python :: 3
Classifier: License :: OSI Approved :: GNU General Public License v3 (GPLv3)
Classifier: Operating System :: OS Independent
